d8s_uuids/__init__.py
d8s_uuids/uuids.py
tests/__init__.py
tests/test_uuids.py
d8s_uuids-0.6.0.dist-info/COPYING
d8s_uuids-0.6.0.dist-info/COPYING.LESSER
d8s_uuids-0.6.0.dist-info/METADATA
d8s_uuids-0.6.0.dist-info/WHEEL
d8s_uuids-0.6.0.dist-info/top_level.txt
d8s_uuids-0.6.0.dist-info/zip-safe
d8s_uuids-0.6.0.dist-info/RECORD
